LICENSE.md
README.md
setup.py
attributee/__init__.py
attributee/containers.py
attributee/io.py
attributee/object.py
attributee/primitives.py
attributee/tests.py
attributee.egg-info/PKG-INFO
attributee.egg-info/SOURCES.txt
attributee.egg-info/dependency_links.txt
attributee.egg-info/top_level.txt