Metadata-Version: 2.1
Name: attributee
Version: 0.1.5
Summary: Declarative object initialization library
Home-page: https://github.com/lukacu/attributee
Author: Luka Cehovin Zajc
Author-email: luka.cehovin@gmail.com
License: UNKNOWN
Platform: UNKNOWN
Classifier: Programming Language :: Python :: 3
Classifier: License :: OSI Approved :: BSD License
Classifier: Operating System :: OS Independent
Classifier: Development Status :: 4 - Beta
Requires-Python: >=3.5
